ETS_CookBook/ETS_CookBook.py
ETS_CookBook/__init__.py
ETS_CookBook/py.typed
ETS_CookBook/ETS_CookBook.egg-info/PKG-INFO
ETS_CookBook/ETS_CookBook.egg-info/SOURCES.txt
ETS_CookBook/ETS_CookBook.egg-info/dependency_links.txt
ETS_CookBook/ETS_CookBook.egg-info/requires.txt
ETS_CookBook/ETS_CookBook.egg-info/top_level.txt
ETS_CookBook/__pycache__/ETS_CookBook.cpython-312.pyc
ets_cookbook-1.2.2.dist-info/licenses/LICENCE
ets_cookbook-1.2.2.dist-info/licenses/LICENSE
ets_cookbook-1.2.2.dist-info/METADATA
ets_cookbook-1.2.2.dist-info/PKG-INFO-PC-28624
ets_cookbook-1.2.2.dist-info/SOURCES-PC-28624.txt
ets_cookbook-1.2.2.dist-info/WHEEL
ets_cookbook-1.2.2.dist-info/requires-PC-28624.txt
ets_cookbook-1.2.2.dist-info/top_level.txt
ets_cookbook-1.2.2.dist-info/RECORD
