Metadata-Version: 2.4
Name: ETS_CookBook
Version: 1.2.2
Summary: The ETS (TNO) CookBook of useful Python Scripts
Author-email: Omar Usmani <Omar.Usmani@TNO.nl>
Project-URL: Homepage, https://github.com/TNO/ETS_CookBook
Classifier: Programming Language :: Python :: 3
Classifier: License :: OSI Approved :: Apache Software License
Classifier: Operating System :: OS Independent
Requires-Python: >=3.11
License-File: LICENCE
License-File: LICENSE
Requires-Dist: dash>=3.04
Requires-Dist: geopandas>=1.0.1
Requires-Dist: Jinja2>=3.1.6
Requires-Dist: matplotlib>=3.9.2
Requires-Dist: numpy>=2.1.3
Requires-Dist: openpyxl>=3.1.5
Requires-Dist: pandas>=2.2.3
Requires-Dist: plotly>=5.24.1
Requires-Dist: python-box>=7.3.2
Requires-Dist: python-docx>=1.1.2
Requires-Dist: requests>=2.32.3
Requires-Dist: xarray>=2024.10.0
Dynamic: license-file
